beepy_network_manager/api.py
beepy_network_manager/cli.py
beepy_network_manager/main.py
beepy_network_manager/tui.py
beepy_network_manager-1.2.2.dist-info/LICENSE
beepy_network_manager-1.2.2.dist-info/METADATA
beepy_network_manager-1.2.2.dist-info/WHEEL
beepy_network_manager-1.2.2.dist-info/entry_points.txt
beepy_network_manager-1.2.2.dist-info/RECORD
