Metadata-Version: 2.1
Name: beepy_network_manager
Version: 1.2.2
Summary: Beepy app to manage WiFi networks
Home-page: https://github.com/conor-f/beepy-network-manager
License: GPLv3
Author: conor-f
Author-email: beepy@randombits.host
Requires-Python: >=3.9,<4.0
Classifier: License :: Other/Proprietary License
Classifier: Programming Language :: Python :: 3
Classifier: Programming Language :: Python :: 3.9
Classifier: Programming Language :: Python :: 3.10
Classifier: Programming Language :: Python :: 3.11
Classifier: Programming Language :: Python :: 3.12
Classifier: Programming Language :: Python :: 3.13
Requires-Dist: psutil (>=6.0.0,<7.0.0)
Requires-Dist: textual (>=0.82.0,<0.83.0)
Requires-Dist: tomli (>=2.0.1,<3.0.0)
